Workbook

Sheet README
C3: SAEIS — Power BI Financial Dashboard Model
C5: الغرض
C6: نموذج أولي قابل للتعديل والاستيراد إلى Power BI لقياس نقطة التعادل، فترة الاسترداد، وهامش المساهمة.
C8: تنبيه مهم
C9: الأرقام التي تحمل وسم Illustrative placeholder ليست بيانات فعلية عن SAEIS. هي قيم تشغيلية مؤقتة لعرض طريقة عمل النموذج، ويجب استبدالها قبل مشاركة النموذج مع ممولين.
C11: طريقة الاستخدام
C12: 1) عدّل الخلايا الزرقاء في ورقة Inputs. 2) راجع النتائج في Dashboard. 3) استورد PowerBI_Export إلى Power BI Desktop. 4) استخدم مقاييس DAX في ملف الإرشادات المرفق.
C14: تعريفات المقاييس
C15: هامش المساهمة = (الإيراد − التكاليف المتغيرة) ÷ الإيراد. نقطة التعادل بالعملاء = التكاليف الثابتة الشهرية ÷ مساهمة العميل المتكرر الشهرية. فترة الاسترداد = أول شهر يصبح فيه التدفق النقدي التراكمي بعد الاستثمار الأولي غير سالب.
C17: نطاق النموذج
C18: النموذج يغطي إيراد SaaS المتكرر، رسوم التكامل لمرة واحدة، تكلفة الخدمة المتغيرة، التكاليف الثابتة، عدد العملاء، التدفق النقدي التشغيلي، والتدفق التراكمي بعد الاستثمار الأولي.
C20: ملاحظة Power BI
C21: لا يمكن إنشاء ملف PBIX أصلي مباشرة في هذه البيئة؛ تم تجهيز ملف Excel وملف CSV بشكل Power BI-ready، مع دليل استيراد ومقاييس DAX قابلة للنسخ.

Sheet Inputs
C3: SAEIS — Inputs & Assumptions
C5: تعديل الافتراضات هنا فقط؛ الخلايا الزرقاء مدخلات يدوية.
C6: Unit: USD / clients / months
C8: Parameter | D8: Value | E8: Unit | F8: Status | G8: Source / note
C9: Initial funding / investment | D9: 26500 | E9: USD | F9: Known project input | G9: Pitch deck / updated funding slide; user-provided project assumption.
C10: SaaS price per active client / month | D10: 1500 | E10: USD / client / month | F10: Illustrative placeholder | G10: Illustrative placeholder for model mechanics; replace with signed pricing or management-approved pricing.
C11: One-time integration fee per new client | D11: 3000 | E11: USD / new client | F11: Illustrative placeholder | G11: Illustrative placeholder; replace with quoted implementation pricing.
C12: Variable cost per active client / month | D12: 300 | E12: USD / client / month | F12: Illustrative placeholder | G12: Illustrative placeholder; replace with hosting, support, and usage cost evidence.
C13: Variable integration cost per new client | D13: 800 | E13: USD / new client | F13: Illustrative placeholder | G13: Illustrative placeholder; replace with actual connector and implementation cost.
C14: Monthly fixed operating costs | D14: 4500 | E14: USD / month | F14: Illustrative placeholder | G14: Illustrative placeholder; replace with payroll, tools, legal, and administration budget.
C15: Starting active clients | D15: 0 | E15: clients | F15: Model input | G15: Modeling convention; replace with current contracted customers if any.
C16: New clients added per month | D16: 1 | E16: clients / month | F16: Illustrative placeholder | G16: Illustrative placeholder; replace with pipeline conversion evidence.
C17: Forecast months | D17: 24 | E17: months | F17: Model convention | G17: Two-year operating view for a pre-seed planning dashboard.
C18: Target break-even clients from pitch deck | D18: 5 | E18: clients | F18: Derived project target | G18: Midpoint of the 4–6 client target shown in the project pitch deck; not a verified forecast.
C21: Model interpretation
C22: The 4–6 client break-even target from the pitch deck is retained as a management target, while the calculated break-even uses the editable price, variable cost, and fixed cost assumptions above.

Sheet Operating_Model
C3: SAEIS — Monthly Operating Model
C5: Forecast engine used by the Dashboard and Power BI export.
C6: Unit: USD / clients / month
C8: Metric | D8: M1 | E8: M2 | F8: M3 | G8: M4 | H8: M5 | I8: M6 | J8: M7 | K8: M8 | L8: M9 | M8: M10 | N8: M11 | O8: M12 | P8: M13 | Q8: M14 | R8: M15 | S8: M16 | T8: M17 | U8: M18 | V8: M19 | W8: M20 | X8: M21 | Y8: M22 | Z8: M23 | AA8: M24
C9: New clients added | D9: =Inputs!$D$16 -> 1 | E9: =Inputs!$D$16 -> 1 | F9: =Inputs!$D$16 -> 1 | G9: =Inputs!$D$16 -> 1 | H9: =Inputs!$D$16 -> 1 | I9: =Inputs!$D$16 -> 1 | J9: =Inputs!$D$16 -> 1 | K9: =Inputs!$D$16 -> 1 | ... AA9: =Inputs!$D$16 -> 1
C10: Active clients | D10: =Inputs!$D$15+D9 -> 1 | E10: =D10+E9 -> 2 | F10: =E10+F9 -> 3 | G10: =F10+G9 -> 4 | H10: =G10+H9 -> 5 | I10: =H10+I9 -> 6 | J10: =I10+J9 -> 7 | K10: =J10+K9 -> 8 | L10: =K10+L9 -> 9 | ... AA10: =Z10+AA9 -> 24
C11: SaaS revenue | D11: =D10*Inputs!$D$10 -> 1500 | E11: =E10*Inputs!$D$10 -> 3000 | F11: =F10*Inputs!$D$10 -> 4500 | G11: =G10*Inputs!$D$10 -> 6000 | H11: =H10*Inputs!$D$10 -> 7500 | I11: =I10*Inputs!$D$10 -> 9000 | J11: =J10*Inputs!$D$10 -> 10500 | K11: =K10*Inputs!$D$10 -> 12000 | ... AA11: =AA10*Inputs!$D$10 -> 36000
C12: Integration revenue | D12: =D9*Inputs!$D$11 -> 3000 | E12: =E9*Inputs!$D$11 -> 3000 | F12: =F9*Inputs!$D$11 -> 3000 | G12: =G9*Inputs!$D$11 -> 3000 | H12: =H9*Inputs!$D$11 -> 3000 | I12: =I9*Inputs!$D$11 -> 3000 | J12: =J9*Inputs!$D$11 -> 3000 | K12: =K9*Inputs!$D$11 -> 3000 | ... AA12: =AA9*Inputs!$D$11 -> 3000
C13: Total revenue | D13: =SUM(D11:D12) -> 4500 | E13: =SUM(E11:E12) -> 6000 | F13: =SUM(F11:F12) -> 7500 | G13: =SUM(G11:G12) -> 9000 | H13: =SUM(H11:H12) -> 10500 | I13: =SUM(I11:I12) -> 12000 | J13: =SUM(J11:J12) -> 13500 | K13: =SUM(K11:K12) -> 15000 | ... AA13: =SUM(AA11:AA12) -> 39000
C14: Variable SaaS costs | D14: =D10*Inputs!$D$12 -> 300 | E14: =E10*Inputs!$D$12 -> 600 | F14: =F10*Inputs!$D$12 -> 900 | G14: =G10*Inputs!$D$12 -> 1200 | H14: =H10*Inputs!$D$12 -> 1500 | I14: =I10*Inputs!$D$12 -> 1800 | J14: =J10*Inputs!$D$12 -> 2100 | K14: =K10*Inputs!$D$12 -> 2400 | ... AA14: =AA10*Inputs!$D$12 -> 7200
C15: Variable integration costs | D15: =D9*Inputs!$D$13 -> 800 | E15: =E9*Inputs!$D$13 -> 800 | F15: =F9*Inputs!$D$13 -> 800 | G15: =G9*Inputs!$D$13 -> 800 | H15: =H9*Inputs!$D$13 -> 800 | I15: =I9*Inputs!$D$13 -> 800 | J15: =J9*Inputs!$D$13 -> 800 | K15: =K9*Inputs!$D$13 -> 800 | ... AA15: =AA9*Inputs!$D$13 -> 800
C16: Total variable costs | D16: =SUM(D14:D15) -> 1100 | E16: =SUM(E14:E15) -> 1400 | F16: =SUM(F14:F15) -> 1700 | G16: =SUM(G14:G15) -> 2000 | H16: =SUM(H14:H15) -> 2300 | I16: =SUM(I14:I15) -> 2600 | J16: =SUM(J14:J15) -> 2900 | K16: =SUM(K14:K15) -> 3200 | ... AA16: =SUM(AA14:AA15) -> 8000
C17: Contribution profit | D17: =D13-D16 -> 3400 | E17: =E13-E16 -> 4600 | F17: =F13-F16 -> 5800 | G17: =G13-G16 -> 7000 | H17: =H13-H16 -> 8200 | I17: =I13-I16 -> 9400 | J17: =J13-J16 -> 10600 | K17: =K13-K16 -> 11800 | ... AA17: =AA13-AA16 -> 31000
C18: Contribution margin % | D18: =IFERROR(D17/D13,0) -> 0.75555556 | E18: =IFERROR(E17/E13,0) -> 0.76666667 | F18: =IFERROR(F17/F13,0) -> 0.77333333 | G18: =IFERROR(G17/G13,0) -> 0.77777778 | H18: =IFERROR(H17/H13,0) -> 0.78095238 | I18: =IFERROR(I17/I13,0) -> 0.78333333 | J18: =IFERROR(J17/J13,0) -> 0.78518519 | K18: =IFERROR(K17/K13,0) -> 0.78666667 | ... AA18: =IFERROR(AA17/AA13,0) -> 0.79487179
C19: Fixed operating costs | D19: =Inputs!$D$14 -> 4500 | E19: =Inputs!$D$14 -> 4500 | F19: =Inputs!$D$14 -> 4500 | G19: =Inputs!$D$14 -> 4500 | H19: =Inputs!$D$14 -> 4500 | I19: =Inputs!$D$14 -> 4500 | J19: =Inputs!$D$14 -> 4500 | K19: =Inputs!$D$14 -> 4500 | ... AA19: =Inputs!$D$14 -> 4500
C20: Operating cash flow | D20: =D17-D19 -> -1100 | E20: =E17-E19 -> 100 | F20: =F17-F19 -> 1300 | G20: =G17-G19 -> 2500 | H20: =H17-H19 -> 3700 | I20: =I17-I19 -> 4900 | J20: =J17-J19 -> 6100 | K20: =K17-K19 -> 7300 | ... AA20: =AA17-AA19 -> 26500
C21: Cumulative operating cash flow | D21: =D20 -> -1100 | E21: =D21+E20 -> -1000 | F21: =E21+F20 -> 300 | G21: =F21+G20 -> 2800 | H21: =G21+H20 -> 6500 | I21: =H21+I20 -> 11400 | J21: =I21+J20 -> 17500 | K21: =J21+K20 -> 24800 | L21: =K21+L20 -> 33300 | ... AA21: =Z21+AA20 -> 304800
C22: Cumulative project cash flow after initial investment | D22: =-Inputs!$D$9+D21 -> -27600 | E22: =-Inputs!$D$9+E21 -> -27500 | F22: =-Inputs!$D$9+F21 -> -26200 | G22: =-Inputs!$D$9+G21 -> -23700 | H22: =-Inputs!$D$9+H21 -> -20000 | I22: =-Inputs!$D$9+I21 -> -15100 | J22: =-Inputs!$D$9+J21 -> -9000 | K22: =-Inputs!$D$9+K21 -> -1700 | ... AA22: =-Inputs!$D$9+AA21 -> 278300
C23: Payback status | D23: =IF(D22>=0,"Paid back","Not yet") -> Not yet | E23: =IF(E22>=0,"Paid back","Not yet") -> Not yet | F23: =IF(F22>=0,"Paid back","Not yet") -> Not yet | G23: =IF(G22>=0,"Paid back","Not yet") -> Not yet | H23: =IF(H22>=0,"Paid back","Not yet") -> Not yet | I23: =IF(I22>=0,"Paid back","Not yet") -> Not yet | J23: =IF(J22>=0,"Paid back","Not yet") -> Not yet | K23: =IF(K22>=0,"Paid back","Not yet") -> Not yet | ... AA23: =IF(AA22>=0,"Paid back","Not yet") -> Paid back

Sheet Dashboard
C3: SAEIS — Financial Dashboard
C5: لوحة موجزة للممولين: نقطة التعادل، الاسترداد، وهامش المساهمة.
C6: Unit: USD / clients / months
C8: KPI | D8: Result | E8: Definition / interpretation
C9: Initial funding | D9: =Inputs!$D$9 -> 26500 | E9: Investment to recover through operating cash flow.
C10: Monthly contribution / active client | D10: =IFERROR(Inputs!$D$10-Inputs!$D$12,0) -> 1200 | E10: SaaS price less recurring variable service cost.
C11: Contribution margin % | D11: =IFERROR(D10/Inputs!$D$10,0) -> 0.8 | E11: Recurring contribution as a percentage of SaaS revenue.
C12: Calculated break-even clients | D12: =IFERROR(Inputs!$D$14/D10,"N/M") -> 3.75 | E12: Monthly fixed costs divided by recurring contribution per active client.
C13: Break-even recurring MRR | D13: =IFERROR(D12*Inputs!$D$10,"N/M") -> 5625 | E13: Recurring SaaS revenue required to cover fixed costs.
C14: Payback period (months) | D14: =IFERROR(MATCH("Paid back",Operating_Model!$D$23:$AA$23,0),"Not reached") -> 9 | E14: First forecast month where project cash flow after initial investment is non-negative.
C15: Cumulative project cash flow at M24 | D15: =Operating_Model!$AA$22 -> 278300 | E15: Cash generated after initial investment in the 24-month base case.
C18: Investor interpretation
C19: The calculated break-even and payback outputs are scenario-dependent. Replace all illustrative placeholders in Inputs before presenting these figures externally.

Sheet PowerBI_Export
C8: Scenario | D8: Month | E8: New Clients | F8: Active Clients | G8: SaaS Revenue | H8: Integration Revenue | I8: Total Revenue | J8: Variable Costs | K8: Contribution Profit | L8: Contribution Margin % | M8: Fixed Operating Costs | N8: Operating Cash Flow | O8: Cumulative Project Cash Flow
C9: Illustrative Base Case | D9: 1 | E9: 1 | F9: 1 | G9: 1500 | H9: 3000 | I9: 4500 | J9: 1100 | K9: 3400 | L9: 0.75555556 | M9: 4500 | N9: -1100 | O9: -27600
C10: Illustrative Base Case | D10: 2 | E10: 1 | F10: 2 | G10: 3000 | H10: 3000 | I10: 6000 | J10: 1400 | K10: 4600 | L10: 0.76666667 | M10: 4500 | N10: 100 | O10: -27500
C11: Illustrative Base Case | D11: 3 | E11: 1 | F11: 3 | G11: 4500 | H11: 3000 | I11: 7500 | J11: 1700 | K11: 5800 | L11: 0.77333333 | M11: 4500 | N11: 1300 | O11: -26200
C12: Illustrative Base Case | D12: 4 | E12: 1 | F12: 4 | G12: 6000 | H12: 3000 | I12: 9000 | J12: 2000 | K12: 7000 | L12: 0.77777778 | M12: 4500 | N12: 2500 | O12: -23700
C13: Illustrative Base Case | D13: 5 | E13: 1 | F13: 5 | G13: 7500 | H13: 3000 | I13: 10500 | J13: 2300 | K13: 8200 | L13: 0.78095238 | M13: 4500 | N13: 3700 | O13: -20000
C14: Illustrative Base Case | D14: 6 | E14: 1 | F14: 6 | G14: 9000 | H14: 3000 | I14: 12000 | J14: 2600 | K14: 9400 | L14: 0.78333333 | M14: 4500 | N14: 4900 | O14: -15100
C15: Illustrative Base Case | D15: 7 | E15: 1 | F15: 7 | G15: 10500 | H15: 3000 | I15: 13500 | J15: 2900 | K15: 10600 | L15: 0.78518519 | M15: 4500 | N15: 6100 | O15: -9000
C16: Illustrative Base Case | D16: 8 | E16: 1 | F16: 8 | G16: 12000 | H16: 3000 | I16: 15000 | J16: 3200 | K16: 11800 | L16: 0.78666667 | M16: 4500 | N16: 7300 | O16: -1700
C17: Illustrative Base Case | D17: 9 | E17: 1 | F17: 9 | G17: 13500 | H17: 3000 | I17: 16500 | J17: 3500 | K17: 13000 | L17: 0.78787879 | M17: 4500 | N17: 8500 | O17: 6800
C18: Illustrative Base Case | D18: 10 | E18: 1 | F18: 10 | G18: 15000 | H18: 3000 | I18: 18000 | J18: 3800 | K18: 14200 | L18: 0.78888889 | M18: 4500 | N18: 9700 | O18: 16500
C19: Illustrative Base Case | D19: 11 | E19: 1 | F19: 11 | G19: 16500 | H19: 3000 | I19: 19500 | J19: 4100 | K19: 15400 | L19: 0.78974359 | M19: 4500 | N19: 10900 | O19: 27400
C20: Illustrative Base Case | D20: 12 | E20: 1 | F20: 12 | G20: 18000 | H20: 3000 | I20: 21000 | J20: 4400 | K20: 16600 | L20: 0.79047619 | M20: 4500 | N20: 12100 | O20: 39500
... C32: Illustrative Base Case | D32: 24 | E32: 1 | F32: 24 | G32: 36000 | H32: 3000 | I32: 39000 | J32: 8000 | K32: 31000 | L32: 0.79487179 | M32: 4500 | N32: 26500 | O32: 278300

Sheet Sensitivity
C3: SAEIS — Break-even Sensitivity
C5: اختبار حساسية نقطة التعادل عند تغيير السعر والتكلفة المتغيرة.
C6: Unit: Clients
C8: Monthly fixed cost / SaaS price | D8: 1000 | E8: 1500 | F8: 2000 | G8: 2500
C9: 3000 | D9: =IFERROR($C9/(D$8-Inputs!$D$12),"N/M") -> 4.2857143 | E9: =IFERROR($C9/(E$8-Inputs!$D$12),"N/M") -> 2.5 | F9: =IFERROR($C9/(F$8-Inputs!$D$12),"N/M") -> 1.7647059 | G9: =IFERROR($C9/(G$8-Inputs!$D$12),"N/M") -> 1.3636364
C10: 4500 | D10: =IFERROR($C10/(D$8-Inputs!$D$12),"N/M") -> 6.4285714 | E10: =IFERROR($C10/(E$8-Inputs!$D$12),"N/M") -> 3.75 | F10: =IFERROR($C10/(F$8-Inputs!$D$12),"N/M") -> 2.6470588 | G10: =IFERROR($C10/(G$8-Inputs!$D$12),"N/M") -> 2.0454545
C11: 6000 | D11: =IFERROR($C11/(D$8-Inputs!$D$12),"N/M") -> 8.5714286 | E11: =IFERROR($C11/(E$8-Inputs!$D$12),"N/M") -> 5 | F11: =IFERROR($C11/(F$8-Inputs!$D$12),"N/M") -> 3.5294118 | G11: =IFERROR($C11/(G$8-Inputs!$D$12),"N/M") -> 2.7272727
C12: 7500 | D12: =IFERROR($C12/(D$8-Inputs!$D$12),"N/M") -> 10.714286 | E12: =IFERROR($C12/(E$8-Inputs!$D$12),"N/M") -> 6.25 | F12: =IFERROR($C12/(F$8-Inputs!$D$12),"N/M") -> 4.4117647 | G12: =IFERROR($C12/(G$8-Inputs!$D$12),"N/M") -> 3.4090909
C15: Note: This grid is a scenario analysis using current illustrative variable cost assumptions. Replace price and cost values with approved commercial assumptions.
