Workbook

Sheet README
A1: SAEIS | دليل النموذج المالي ولوحة Power BI
A2: نسخة محدثة مبنية على ملف SAEISSmartAuditPitchDeck-Updated.pdf
A4: الغرض | B4: نموذج تخطيطي قابل للتحرير لتحليل الميزانية، الإيرادات، الأرباح، الانحرافات، نقطة التعادل، وفترة الاسترداد.
A5: البيانات المؤكدة من العرض | B5: أسعار الباقات السنوية: 2,500 دولار للباقة الأساسية، 7,500 دولار للباقة الاحترافية، وباقة المؤسسات حسب المتطلبات. كما يذكر العرض أهداف أثر بنسبة 90% لدقة اكتشاف الأخطاء و60% لتقليل وقت التدقيق.
A6: البيانات القابلة للتحرير | B6: عدد العملاء، سرعة اكتساب العملاء، التكلفة المتغيرة، التكاليف الثابتة، المصروفات الفعلية، وتوزيع الميزانية. القيم الافتراضية في Inputs سيناريو تخطيطي وليست نتائج محققة.
A7: طريقة الاستخدام | B7: عدّل الخلايا الزرقاء في Inputs وActuals_Monthly وBudget_Variance، ثم افتح PowerBI_Export في Power BI أو انسخه إلى نموذج البيانات.
A8: تعريف نقطة التعادل | B8: نقطة التعادل الشهرية = التكاليف الثابتة الشهرية ÷ هامش المساهمة. عدد العملاء المكافئ = نقطة التعادل الشهرية ÷ متوسط الإيراد الشهري للعميل.
A9: تعريف فترة الاسترداد | B9: عدد الأشهر حتى يصبح التدفق النقدي التراكمي بعد طرح التمويل الأولي غير سالب.
A10: ملاحظة مهمة | B10: لا تمثل القيم الافتراضية توقعًا ماليًا نهائيًا. استخدم بيانات العقود والتكاليف الفعلية قبل مشاركة النتائج مع الممولين.

Sheet Inputs
A1: SAEIS | الافتراضات والمدخلات
A2: الخلايا الزرقاء قابلة للتعديل. المصادر المعلّمة من العرض، بينما الافتراضات التشغيلية تحتاج إلى تحقق من الفريق.
A4: الفئة | B4: المتغير | C4: القيمة | D4: الوحدة | E4: الحالة | F4: المصدر أو الملاحظة
A5: تمويل | B5: طلب التمويل | C5: 26500 | D5: دولار | E5: مدخل من سياق المشروع | F5: مبلغ طلب التمويل المذكور سابقًا في العرض.
A6: التسعير | B6: الباقة الأساسية سنويًا | C6: 2500 | D6: دولار | E6: من العرض | F6: المنشآت الصغيرة.
A7: التسعير | B7: الباقة الاحترافية سنويًا | C7: 7500 | D7: دولار | E7: من العرض | F7: الشركات المتوسطة.
A8: التسعير | B8: باقة المؤسسات سنويًا | C8: 0 | D8: دولار | E8: يحتاج إدخالًا | F8: السعر حسب المتطلبات، لذلك يترك صفرًا حتى يحدد الفريق السعر.
A9: العملاء | B9: عملاء أساسيون عند البداية | C9: 0 | D9: عميل | E9: افتراض تخطيطي | F9: عدّل حسب العملاء الحاليين أو التجارب المتوقعة.
A10: العملاء | B10: عملاء احترافيون عند البداية | C10: 0 | D10: عميل | E10: افتراض تخطيطي | F10: عدّل حسب العملاء الحاليين أو التجارب المتوقعة.
A11: العملاء | B11: عملاء مؤسسات عند البداية | C11: 0 | D11: عميل | E11: افتراض تخطيطي | F11: اتركه صفرًا حتى تتوافر عقود المؤسسات.
A12: النمو | B12: عملاء أساسيون جدد شهريًا | C12: 0.5 | D12: عميل/شهر | E12: افتراض تخطيطي | F12: قابل للتغيير إلى خطة المبيعات الواقعية.
A13: النمو | B13: عملاء احترافيون جدد شهريًا | C13: 0.25 | D13: عميل/شهر | E13: افتراض تخطيطي | F13: قابل للتغيير إلى خطة المبيعات الواقعية.
A14: النمو | B14: عملاء مؤسسات جدد شهريًا | C14: 0 | D14: عميل/شهر | E14: افتراض تخطيطي | F14: يتطلب سعرًا سنويًا مدخلًا.
A15: التكلفة | B15: معدل الانسحاب الشهري | C15: 0 | D15: % | E15: افتراض تخطيطي | F15: عدّل بعد توفر بيانات الاحتفاظ.
A16: التكلفة | B16: التكلفة المتغيرة كنسبة من الإيراد | C16: 0.2 | D16: % | E16: افتراض تخطيطي | F16: تستخدم لحساب هامش المساهمة.
... A20: الأثر | B20: هدف خفض وقت التدقيق | C20: 0.6 | D20: % | E20: هدف من العرض | F20: يعرض كهدف أداء وليس نتيجة فعلية.

Sheet Budget_Variance
A1: SAEIS | الميزانية والانحرافات
A2: أدخل المصروف الفعلي في الخلايا الزرقاء. الانحراف الإيجابي في المصروفات يعني تجاوز الميزانية.
A4: البند | B4: الميزانية المخططة | C4: الفعلي | D4: الانحراف | E4: الانحراف % | F4: الحالة | G4: المخرج المرتبط
A5: بناء المنتج والنسخة التجريبية | B5: 11925 | D5: =IF(C5="","",C5-B5) | E5: =IF(C5="","",IF(B5=0,"",D5/B5)) | F5: =IF(C5="","أدخل الفعلي",IF(D5>0,"تجاوز",IF(D5<0,"أقل من الميزانية","مطابق"))) -> أدخل الفعلي | G5: MVP قابل للتشغيل
A6: التكامل والأمان والامتثال التقني | B6: 6625 | D6: =IF(C6="","",C6-B6) | E6: =IF(C6="","",IF(B6=0,"",D6/B6)) | F6: =IF(C6="","أدخل الفعلي",IF(D6>0,"تجاوز",IF(D6<0,"أقل من الميزانية","مطابق"))) -> أدخل الفعلي | G6: موصل ERP وبيئة تجربة آمنة
A7: إثبات السوق وتجربة العملاء | B7: 5300 | D7: =IF(C7="","",C7-B7) | E7: =IF(C7="","",IF(B7=0,"",D7/B7)) | F7: =IF(C7="","أدخل الفعلي",IF(D7>0,"تجاوز",IF(D7<0,"أقل من الميزانية","مطابق"))) -> أدخل الفعلي | G7: تجارب عميل ودراسة حالة
A8: التشغيل والامتثال الإداري | B8: 2650 | D8: =IF(C8="","",C8-B8) | E8: =IF(C8="","",IF(B8=0,"",D8/B8)) | F8: =IF(C8="","أدخل الفعلي",IF(D8>0,"تجاوز",IF(D8<0,"أقل من الميزانية","مطابق"))) -> أدخل الفعلي | G8: جاهزية تشغيلية وقانونية
A10: الإجمالي | B10: =SUM(B5:B8) -> 26500 | C10: =IF(COUNTA(C5:C8)=0,"",SUM(C5:C8)) | D10: =IF(C10="","",C10-B10) | E10: =IF(C10="","",D10/B10) | F10: =IF(C10="","أدخل الفعلي",IF(D10>0,"تجاوز",IF(D10<0,"أقل من الميزانية","مطابق"))) -> أدخل الفعلي

Sheet Actuals_Monthly
A1: SAEIS | المدخلات الفعلية الشهرية
A2: أدخل القيم الفعلية المتاحة. الخلايا الفارغة لا تُعامل كصفر داخل مقارنة الأداء.
A4: الشهر | B4: الإيراد الفعلي | C4: التكلفة المتغيرة الفعلية | D4: التكاليف الثابتة الفعلية | E4: مصروفات أخرى فعلية | F4: ملاحظات
A5: 1 | F5: أدخل البيانات الفعلية عند توفرها
A6: 2 | F6: أدخل البيانات الفعلية عند توفرها
A7: 3 | F7: أدخل البيانات الفعلية عند توفرها
A8: 4 | F8: أدخل البيانات الفعلية عند توفرها
A9: 5 | F9: أدخل البيانات الفعلية عند توفرها
A10: 6 | F10: أدخل البيانات الفعلية عند توفرها
A11: 7 | F11: أدخل البيانات الفعلية عند توفرها
A12: 8 | F12: أدخل البيانات الفعلية عند توفرها
A13: 9 | F13: أدخل البيانات الفعلية عند توفرها
A14: 10 | F14: أدخل البيانات الفعلية عند توفرها
A15: 11 | F15: أدخل البيانات الفعلية عند توفرها
A16: 12 | F16: أدخل البيانات الفعلية عند توفرها
... A28: 24 | F28: أدخل البيانات الفعلية عند توفرها

Sheet Monthly_Model
A1: SAEIS | النموذج التشغيلي الشهري
A2: الجزء الأخضر يمثل الخطة/السيناريو، والجزء الأزرق يُسحب من Actuals_Monthly عند إدخال الفعلي.
A4: الشهر | B4: الربع | C4: عملاء أساسيون | D4: عملاء احترافيون | E4: عملاء مؤسسات | F4: إجمالي العملاء | G4: إيراد أساسي | H4: إيراد احترافي | I4: إيراد مؤسسات | J4: إجمالي الإيراد المخطط | K4: التكلفة المتغيرة المخططة | L4: التكاليف الثابتة المخططة | M4: الربح التشغيلي المخطط | N4: التدفق التراكمي المخطط | O4: هامش المساهمة | P4: الإيراد الفعلي | Q4: الربح الفعلي | R4: انحراف الإيراد | S4: انحراف الربح | T4: حالة الفعلي | U4: Payback Flag
A5: 1 | B5: ="Q"&ROUNDUP(A5/3,0) -> Q1 | C5: =Inputs!$C$9*(1-Inputs!$C$15)+Inputs!$C$12 -> 0.5 | D5: =Inputs!$C$10*(1-Inputs!$C$15)+Inputs!$C$13 -> 0.25 | E5: =Inputs!$C$11*(1-Inputs!$C$15)+Inputs!$C$14 -> 0 | F5: =SUM(C5:E5) -> 0.75 | G5: =C5*Inputs!$C$6/12 -> 104.16667 | H5: =D5*Inputs!$C$7/12 -> 156.25 | I5: =E5*Inputs!$C$8/12 -> 0 | J5: =SUM(G5:I5) -> 260.41667 | K5: =J5*Inputs!$C$16 -> 52.083333 | L5: =Inputs!$C$17 -> 4500 | M5: =J5-K5-L5 -> -4291.6667 | N5: =-Inputs!$C$5+M5 -> -30791.667 | O5: =IF(J5=0,"",(J5-K5)/J5) -> 0.8 | P5: =IF(Actuals_Monthly!B5="","",Actuals_Monthly!B5) | Q5: =IF(OR(Actuals_Monthly!B5="",Actuals_Monthly!C5="",Actuals_Monthly!D5=""),"",Actuals_Monthly!B5-Actuals_Monthly!C5-Actuals_Monthly!D5) | R5: =IF(P5="","",P5-J5) | S5: =IF(Q5="","",Q5-M5) | T5: =IF(P5="","أدخل الفعلي",IF(R5>=0,"فوق الخطة","دون الخطة")) -> أدخل الفعلي | U5: =IF(N5>=0,1,0) -> 0
A6: 2 | B6: ="Q"&ROUNDUP(A6/3,0) -> Q1 | C6: =C5*(1-Inputs!$C$15)+Inputs!$C$12 -> 1 | D6: =D5*(1-Inputs!$C$15)+Inputs!$C$13 -> 0.5 | E6: =E5*(1-Inputs!$C$15)+Inputs!$C$14 -> 0 | F6: =SUM(C6:E6) -> 1.5 | G6: =C6*Inputs!$C$6/12 -> 208.33333 | H6: =D6*Inputs!$C$7/12 -> 312.5 | I6: =E6*Inputs!$C$8/12 -> 0 | J6: =SUM(G6:I6) -> 520.83333 | K6: =J6*Inputs!$C$16 -> 104.16667 | L6: =Inputs!$C$17 -> 4500 | M6: =J6-K6-L6 -> -4083.3333 | N6: =N5+M6 -> -34875 | O6: =IF(J6=0,"",(J6-K6)/J6) -> 0.8 | P6: =IF(Actuals_Monthly!B6="","",Actuals_Monthly!B6) | Q6: =IF(OR(Actuals_Monthly!B6="",Actuals_Monthly!C6="",Actuals_Monthly!D6=""),"",Actuals_Monthly!B6-Actuals_Monthly!C6-Actuals_Monthly!D6) | R6: =IF(P6="","",P6-J6) | S6: =IF(Q6="","",Q6-M6) | T6: =IF(P6="","أدخل الفعلي",IF(R6>=0,"فوق الخطة","دون الخطة")) -> أدخل الفعلي | U6: =IF(N6>=0,1,0) -> 0
A7: 3 | B7: ="Q"&ROUNDUP(A7/3,0) -> Q1 | C7: =C6*(1-Inputs!$C$15)+Inputs!$C$12 -> 1.5 | D7: =D6*(1-Inputs!$C$15)+Inputs!$C$13 -> 0.75 | E7: =E6*(1-Inputs!$C$15)+Inputs!$C$14 -> 0 | F7: =SUM(C7:E7) -> 2.25 | G7: =C7*Inputs!$C$6/12 -> 312.5 | H7: =D7*Inputs!$C$7/12 -> 468.75 | I7: =E7*Inputs!$C$8/12 -> 0 | J7: =SUM(G7:I7) -> 781.25 | K7: =J7*Inputs!$C$16 -> 156.25 | L7: =Inputs!$C$17 -> 4500 | M7: =J7-K7-L7 -> -3875 | N7: =N6+M7 -> -38750 | O7: =IF(J7=0,"",(J7-K7)/J7) -> 0.8 | P7: =IF(Actuals_Monthly!B7="","",Actuals_Monthly!B7) | Q7: =IF(OR(Actuals_Monthly!B7="",Actuals_Monthly!C7="",Actuals_Monthly!D7=""),"",Actuals_Monthly!B7-Actuals_Monthly!C7-Actuals_Monthly!D7) | R7: =IF(P7="","",P7-J7) | S7: =IF(Q7="","",Q7-M7) | T7: =IF(P7="","أدخل الفعلي",IF(R7>=0,"فوق الخطة","دون الخطة")) -> أدخل الفعلي | U7: =IF(N7>=0,1,0) -> 0
A8: 4 | B8: ="Q"&ROUNDUP(A8/3,0) -> Q2 | C8: =C7*(1-Inputs!$C$15)+Inputs!$C$12 -> 2 | D8: =D7*(1-Inputs!$C$15)+Inputs!$C$13 -> 1 | E8: =E7*(1-Inputs!$C$15)+Inputs!$C$14 -> 0 | F8: =SUM(C8:E8) -> 3 | G8: =C8*Inputs!$C$6/12 -> 416.66667 | H8: =D8*Inputs!$C$7/12 -> 625 | I8: =E8*Inputs!$C$8/12 -> 0 | J8: =SUM(G8:I8) -> 1041.6667 | K8: =J8*Inputs!$C$16 -> 208.33333 | L8: =Inputs!$C$17 -> 4500 | M8: =J8-K8-L8 -> -3666.6667 | N8: =N7+M8 -> -42416.667 | O8: =IF(J8=0,"",(J8-K8)/J8) -> 0.8 | P8: =IF(Actuals_Monthly!B8="","",Actuals_Monthly!B8) | Q8: =IF(OR(Actuals_Monthly!B8="",Actuals_Monthly!C8="",Actuals_Monthly!D8=""),"",Actuals_Monthly!B8-Actuals_Monthly!C8-Actuals_Monthly!D8) | R8: =IF(P8="","",P8-J8) | S8: =IF(Q8="","",Q8-M8) | T8: =IF(P8="","أدخل الفعلي",IF(R8>=0,"فوق الخطة","دون الخطة")) -> أدخل الفعلي | U8: =IF(N8>=0,1,0) -> 0
A9: 5 | B9: ="Q"&ROUNDUP(A9/3,0) -> Q2 | C9: =C8*(1-Inputs!$C$15)+Inputs!$C$12 -> 2.5 | D9: =D8*(1-Inputs!$C$15)+Inputs!$C$13 -> 1.25 | E9: =E8*(1-Inputs!$C$15)+Inputs!$C$14 -> 0 | F9: =SUM(C9:E9) -> 3.75 | G9: =C9*Inputs!$C$6/12 -> 520.83333 | H9: =D9*Inputs!$C$7/12 -> 781.25 | I9: =E9*Inputs!$C$8/12 -> 0 | J9: =SUM(G9:I9) -> 1302.0833 | K9: =J9*Inputs!$C$16 -> 260.41667 | L9: =Inputs!$C$17 -> 4500 | M9: =J9-K9-L9 -> -3458.3333 | N9: =N8+M9 -> -45875 | O9: =IF(J9=0,"",(J9-K9)/J9) -> 0.8 | P9: =IF(Actuals_Monthly!B9="","",Actuals_Monthly!B9) | Q9: =IF(OR(Actuals_Monthly!B9="",Actuals_Monthly!C9="",Actuals_Monthly!D9=""),"",Actuals_Monthly!B9-Actuals_Monthly!C9-Actuals_Monthly!D9) | R9: =IF(P9="","",P9-J9) | S9: =IF(Q9="","",Q9-M9) | T9: =IF(P9="","أدخل الفعلي",IF(R9>=0,"فوق الخطة","دون الخطة")) -> أدخل الفعلي | U9: =IF(N9>=0,1,0) -> 0
A10: 6 | B10: ="Q"&ROUNDUP(A10/3,0) -> Q2 | C10: =C9*(1-Inputs!$C$15)+Inputs!$C$12 -> 3 | D10: =D9*(1-Inputs!$C$15)+Inputs!$C$13 -> 1.5 | E10: =E9*(1-Inputs!$C$15)+Inputs!$C$14 -> 0 | F10: =SUM(C10:E10) -> 4.5 | G10: =C10*Inputs!$C$6/12 -> 625 | H10: =D10*Inputs!$C$7/12 -> 937.5 | I10: =E10*Inputs!$C$8/12 -> 0 | J10: =SUM(G10:I10) -> 1562.5 | K10: =J10*Inputs!$C$16 -> 312.5 | L10: =Inputs!$C$17 -> 4500 | M10: =J10-K10-L10 -> -3250 | N10: =N9+M10 -> -49125 | O10: =IF(J10=0,"",(J10-K10)/J10) -> 0.8 | P10: =IF(Actuals_Monthly!B10="","",Actuals_Monthly!B10) | Q10: =IF(OR(Actuals_Monthly!B10="",Actuals_Monthly!C10="",Actuals_Monthly!D10=""),"",Actuals_Monthly!B10-Actuals_Monthly!C10-Actuals_Monthly!D10) | R10: =IF(P10="","",P10-J10) | S10: =IF(Q10="","",Q10-M10) | T10: =IF(P10="","أدخل الفعلي",IF(R10>=0,"فوق الخطة","دون الخطة")) -> أدخل الفعلي | U10: =IF(N10>=0,1,0) -> 0
A11: 7 | B11: ="Q"&ROUNDUP(A11/3,0) -> Q3 | C11: =C10*(1-Inputs!$C$15)+Inputs!$C$12 -> 3.5 | D11: =D10*(1-Inputs!$C$15)+Inputs!$C$13 -> 1.75 | E11: =E10*(1-Inputs!$C$15)+Inputs!$C$14 -> 0 | F11: =SUM(C11:E11) -> 5.25 | G11: =C11*Inputs!$C$6/12 -> 729.16667 | H11: =D11*Inputs!$C$7/12 -> 1093.75 | I11: =E11*Inputs!$C$8/12 -> 0 | J11: =SUM(G11:I11) -> 1822.9167 | K11: =J11*Inputs!$C$16 -> 364.58333 | L11: =Inputs!$C$17 -> 4500 | M11: =J11-K11-L11 -> -3041.6667 | N11: =N10+M11 -> -52166.667 | O11: =IF(J11=0,"",(J11-K11)/J11) -> 0.8 | P11: =IF(Actuals_Monthly!B11="","",Actuals_Monthly!B11) | Q11: =IF(OR(Actuals_Monthly!B11="",Actuals_Monthly!C11="",Actuals_Monthly!D11=""),"",Actuals_Monthly!B11-Actuals_Monthly!C11-Actuals_Monthly!D11) | R11: =IF(P11="","",P11-J11) | S11: =IF(Q11="","",Q11-M11) | T11: =IF(P11="","أدخل الفعلي",IF(R11>=0,"فوق الخطة","دون الخطة")) -> أدخل الفعلي | U11: =IF(N11>=0,1,0) -> 0
A12: 8 | B12: ="Q"&ROUNDUP(A12/3,0) -> Q3 | C12: =C11*(1-Inputs!$C$15)+Inputs!$C$12 -> 4 | D12: =D11*(1-Inputs!$C$15)+Inputs!$C$13 -> 2 | E12: =E11*(1-Inputs!$C$15)+Inputs!$C$14 -> 0 | F12: =SUM(C12:E12) -> 6 | G12: =C12*Inputs!$C$6/12 -> 833.33333 | H12: =D12*Inputs!$C$7/12 -> 1250 | I12: =E12*Inputs!$C$8/12 -> 0 | J12: =SUM(G12:I12) -> 2083.3333 | K12: =J12*Inputs!$C$16 -> 416.66667 | L12: =Inputs!$C$17 -> 4500 | M12: =J12-K12-L12 -> -2833.3333 | N12: =N11+M12 -> -55000 | O12: =IF(J12=0,"",(J12-K12)/J12) -> 0.8 | P12: =IF(Actuals_Monthly!B12="","",Actuals_Monthly!B12) | Q12: =IF(OR(Actuals_Monthly!B12="",Actuals_Monthly!C12="",Actuals_Monthly!D12=""),"",Actuals_Monthly!B12-Actuals_Monthly!C12-Actuals_Monthly!D12) | R12: =IF(P12="","",P12-J12) | S12: =IF(Q12="","",Q12-M12) | T12: =IF(P12="","أدخل الفعلي",IF(R12>=0,"فوق الخطة","دون الخطة")) -> أدخل الفعلي | U12: =IF(N12>=0,1,0) -> 0
A13: 9 | B13: ="Q"&ROUNDUP(A13/3,0) -> Q3 | C13: =C12*(1-Inputs!$C$15)+Inputs!$C$12 -> 4.5 | D13: =D12*(1-Inputs!$C$15)+Inputs!$C$13 -> 2.25 | E13: =E12*(1-Inputs!$C$15)+Inputs!$C$14 -> 0 | F13: =SUM(C13:E13) -> 6.75 | G13: =C13*Inputs!$C$6/12 -> 937.5 | H13: =D13*Inputs!$C$7/12 -> 1406.25 | I13: =E13*Inputs!$C$8/12 -> 0 | J13: =SUM(G13:I13) -> 2343.75 | K13: =J13*Inputs!$C$16 -> 468.75 | L13: =Inputs!$C$17 -> 4500 | M13: =J13-K13-L13 -> -2625 | N13: =N12+M13 -> -57625 | O13: =IF(J13=0,"",(J13-K13)/J13) -> 0.8 | P13: =IF(Actuals_Monthly!B13="","",Actuals_Monthly!B13) | Q13: =IF(OR(Actuals_Monthly!B13="",Actuals_Monthly!C13="",Actuals_Monthly!D13=""),"",Actuals_Monthly!B13-Actuals_Monthly!C13-Actuals_Monthly!D13) | R13: =IF(P13="","",P13-J13) | S13: =IF(Q13="","",Q13-M13) | T13: =IF(P13="","أدخل الفعلي",IF(R13>=0,"فوق الخطة","دون الخطة")) -> أدخل الفعلي | U13: =IF(N13>=0,1,0) -> 0
A14: 10 | B14: ="Q"&ROUNDUP(A14/3,0) -> Q4 | C14: =C13*(1-Inputs!$C$15)+Inputs!$C$12 -> 5 | D14: =D13*(1-Inputs!$C$15)+Inputs!$C$13 -> 2.5 | E14: =E13*(1-Inputs!$C$15)+Inputs!$C$14 -> 0 | F14: =SUM(C14:E14) -> 7.5 | G14: =C14*Inputs!$C$6/12 -> 1041.6667 | H14: =D14*Inputs!$C$7/12 -> 1562.5 | I14: =E14*Inputs!$C$8/12 -> 0 | J14: =SUM(G14:I14) -> 2604.1667 | K14: =J14*Inputs!$C$16 -> 520.83333 | L14: =Inputs!$C$17 -> 4500 | M14: =J14-K14-L14 -> -2416.6667 | N14: =N13+M14 -> -60041.667 | O14: =IF(J14=0,"",(J14-K14)/J14) -> 0.8 | P14: =IF(Actuals_Monthly!B14="","",Actuals_Monthly!B14) | Q14: =IF(OR(Actuals_Monthly!B14="",Actuals_Monthly!C14="",Actuals_Monthly!D14=""),"",Actuals_Monthly!B14-Actuals_Monthly!C14-Actuals_Monthly!D14) | R14: =IF(P14="","",P14-J14) | S14: =IF(Q14="","",Q14-M14) | T14: =IF(P14="","أدخل الفعلي",IF(R14>=0,"فوق الخطة","دون الخطة")) -> أدخل الفعلي | U14: =IF(N14>=0,1,0) -> 0
A15: 11 | B15: ="Q"&ROUNDUP(A15/3,0) -> Q4 | C15: =C14*(1-Inputs!$C$15)+Inputs!$C$12 -> 5.5 | D15: =D14*(1-Inputs!$C$15)+Inputs!$C$13 -> 2.75 | E15: =E14*(1-Inputs!$C$15)+Inputs!$C$14 -> 0 | F15: =SUM(C15:E15) -> 8.25 | G15: =C15*Inputs!$C$6/12 -> 1145.8333 | H15: =D15*Inputs!$C$7/12 -> 1718.75 | I15: =E15*Inputs!$C$8/12 -> 0 | J15: =SUM(G15:I15) -> 2864.5833 | K15: =J15*Inputs!$C$16 -> 572.91667 | L15: =Inputs!$C$17 -> 4500 | M15: =J15-K15-L15 -> -2208.3333 | N15: =N14+M15 -> -62250 | O15: =IF(J15=0,"",(J15-K15)/J15) -> 0.8 | P15: =IF(Actuals_Monthly!B15="","",Actuals_Monthly!B15) | Q15: =IF(OR(Actuals_Monthly!B15="",Actuals_Monthly!C15="",Actuals_Monthly!D15=""),"",Actuals_Monthly!B15-Actuals_Monthly!C15-Actuals_Monthly!D15) | R15: =IF(P15="","",P15-J15) | S15: =IF(Q15="","",Q15-M15) | T15: =IF(P15="","أدخل الفعلي",IF(R15>=0,"فوق الخطة","دون الخطة")) -> أدخل الفعلي | U15: =IF(N15>=0,1,0) -> 0
A16: 12 | B16: ="Q"&ROUNDUP(A16/3,0) -> Q4 | C16: =C15*(1-Inputs!$C$15)+Inputs!$C$12 -> 6 | D16: =D15*(1-Inputs!$C$15)+Inputs!$C$13 -> 3 | E16: =E15*(1-Inputs!$C$15)+Inputs!$C$14 -> 0 | F16: =SUM(C16:E16) -> 9 | G16: =C16*Inputs!$C$6/12 -> 1250 | H16: =D16*Inputs!$C$7/12 -> 1875 | I16: =E16*Inputs!$C$8/12 -> 0 | J16: =SUM(G16:I16) -> 3125 | K16: =J16*Inputs!$C$16 -> 625 | L16: =Inputs!$C$17 -> 4500 | M16: =J16-K16-L16 -> -2000 | N16: =N15+M16 -> -64250 | O16: =IF(J16=0,"",(J16-K16)/J16) -> 0.8 | P16: =IF(Actuals_Monthly!B16="","",Actuals_Monthly!B16) | Q16: =IF(OR(Actuals_Monthly!B16="",Actuals_Monthly!C16="",Actuals_Monthly!D16=""),"",Actuals_Monthly!B16-Actuals_Monthly!C16-Actuals_Monthly!D16) | R16: =IF(P16="","",P16-J16) | S16: =IF(Q16="","",Q16-M16) | T16: =IF(P16="","أدخل الفعلي",IF(R16>=0,"فوق الخطة","دون الخطة")) -> أدخل الفعلي | U16: =IF(N16>=0,1,0) -> 0
A17: 13 | B17: ="Q"&ROUNDUP(A17/3,0) -> Q5 | C17: =C16*(1-Inputs!$C$15)+Inputs!$C$12 -> 6.5 | D17: =D16*(1-Inputs!$C$15)+Inputs!$C$13 -> 3.25 | E17: =E16*(1-Inputs!$C$15)+Inputs!$C$14 -> 0 | F17: =SUM(C17:E17) -> 9.75 | G17: =C17*Inputs!$C$6/12 -> 1354.1667 | H17: =D17*Inputs!$C$7/12 -> 2031.25 | I17: =E17*Inputs!$C$8/12 -> 0 | J17: =SUM(G17:I17) -> 3385.4167 | K17: =J17*Inputs!$C$16 -> 677.08333 | L17: =Inputs!$C$17 -> 4500 | M17: =J17-K17-L17 -> -1791.6667 | N17: =N16+M17 -> -66041.667 | O17: =IF(J17=0,"",(J17-K17)/J17) -> 0.8 | P17: =IF(Actuals_Monthly!B17="","",Actuals_Monthly!B17) | Q17: =IF(OR(Actuals_Monthly!B17="",Actuals_Monthly!C17="",Actuals_Monthly!D17=""),"",Actuals_Monthly!B17-Actuals_Monthly!C17-Actuals_Monthly!D17) | R17: =IF(P17="","",P17-J17) | S17: =IF(Q17="","",Q17-M17) | T17: =IF(P17="","أدخل الفعلي",IF(R17>=0,"فوق الخطة","دون الخطة")) -> أدخل الفعلي | U17: =IF(N17>=0,1,0) -> 0
... A28: 24 | B28: ="Q"&ROUNDUP(A28/3,0) -> Q8 | C28: =C27*(1-Inputs!$C$15)+Inputs!$C$12 -> 12 | D28: =D27*(1-Inputs!$C$15)+Inputs!$C$13 -> 6 | E28: =E27*(1-Inputs!$C$15)+Inputs!$C$14 -> 0 | F28: =SUM(C28:E28) -> 18 | G28: =C28*Inputs!$C$6/12 -> 2500 | H28: =D28*Inputs!$C$7/12 -> 3750 | I28: =E28*Inputs!$C$8/12 -> 0 | J28: =SUM(G28:I28) -> 6250 | K28: =J28*Inputs!$C$16 -> 1250 | L28: =Inputs!$C$17 -> 4500 | M28: =J28-K28-L28 -> 500 | N28: =N27+M28 -> -72000 | O28: =IF(J28=0,"",(J28-K28)/J28) -> 0.8 | P28: =IF(Actuals_Monthly!B28="","",Actuals_Monthly!B28) | Q28: =IF(OR(Actuals_Monthly!B28="",Actuals_Monthly!C28="",Actuals_Monthly!D28=""),"",Actuals_Monthly!B28-Actuals_Monthly!C28-Actuals_Monthly!D28) | R28: =IF(P28="","",P28-J28) | S28: =IF(Q28="","",Q28-M28) | T28: =IF(P28="","أدخل الفعلي",IF(R28>=0,"فوق الخطة","دون الخطة")) -> أدخل الفعلي | U28: =IF(N28>=0,1,0) -> 0

Sheet Dashboard
A1: SAEIS | لوحة المؤشرات المالية والتنفيذية
A2: مؤشرات الخطة الحالية، مع حقول مقارنة الفعلي عند إدخال البيانات. الأرقام الحالية سيناريو تخطيطي قابل للتعديل.
B4: طلب التمويل | C4: =Inputs!$C$5 -> 26500 | E4: الإيراد المخطط في الشهر 12 | F4: =Monthly_Model!J16 -> 3125 | H4: الربح التشغيلي في الشهر 12 | I4: =Monthly_Model!M16 -> -2000 | K4: هامش المساهمة | L4: =Monthly_Model!O16 -> 0.8
B8: نقطة التعادل الشهرية | C8: =Inputs!$C$17/(1-Inputs!$C$16) -> 5625 | E8: عدد العملاء عند التعادل | F8: =IFERROR(C8/(Monthly_Model!J16/Monthly_Model!F16),"") -> 16.2 | H8: فترة الاسترداد | I8: =IFERROR(INDEX(Monthly_Model!A5:A28,MATCH(1,Monthly_Model!U5:U28,0)),"غير محققة") -> غير محققة | K8: التدفق التراكمي في الشهر 24 | L8: =Monthly_Model!N28 -> -72000
B12: الميزانية مقابل الفعلي | H12: أهداف الأثر من العرض
B13: البند | C13: المخطط | D13: الفعلي | E13: الانحراف | F13: الحالة | H13: المؤشر | I13: الهدف | J13: الفعلي | K13: الفجوة
B14: =Budget_Variance!A5 -> بناء المنتج والنسخة التجريبية | C14: =Budget_Variance!B5 -> 11925 | D14: =Budget_Variance!C5 -> 0 | E14: =Budget_Variance!D5 | F14: =Budget_Variance!F5 -> أدخل الفعلي | H14: دقة اكتشاف الأخطاء | I14: =Inputs!C19 -> 0.9 | K14: =IF(J14="","",J14-I14)
B15: =Budget_Variance!A6 -> التكامل والأمان والامتثال التقني | C15: =Budget_Variance!B6 -> 6625 | D15: =Budget_Variance!C6 -> 0 | E15: =Budget_Variance!D6 | F15: =Budget_Variance!F6 -> أدخل الفعلي | H15: خفض وقت التدقيق | I15: =Inputs!C20 -> 0.6 | K15: =IF(J15="","",J15-I15)
B16: =Budget_Variance!A7 -> إثبات السوق وتجربة العملاء | C16: =Budget_Variance!B7 -> 5300 | D16: =Budget_Variance!C7 -> 0 | E16: =Budget_Variance!D7 | F16: =Budget_Variance!F7 -> أدخل الفعلي
B17: =Budget_Variance!A8 -> التشغيل والامتثال الإداري | C17: =Budget_Variance!B8 -> 2650 | D17: =Budget_Variance!C8 -> 0 | E17: =Budget_Variance!D8 | F17: =Budget_Variance!F8 -> أدخل الفعلي
B20: قراءة سريعة للممول
B21: اللوحة تفصل بين الخطة والفعلي: الخطة تُبنى من أسعار الباقات الواردة في العرض، بينما الفعلي يظل فارغًا حتى يدخله الفريق. لذلك فإن أي انحراف أو ربح فعلي لن يظهر إلا بعد إدخال البيانات التشغيلية الحقيقية.

Sheet PowerBI_Export
A1: Month | B1: Quarter | C1: Basic Clients Plan | D1: Professional Clients Plan | E1: Enterprise Clients Plan | F1: Total Clients Plan | G1: Basic Revenue Plan | H1: Professional Revenue Plan | I1: Enterprise Revenue Plan | J1: Total Revenue Plan | K1: Variable Cost Plan | L1: Fixed Opex Plan | M1: Operating Profit Plan | N1: Cumulative Project Cash Plan | O1: Contribution Margin Plan | P1: Actual Revenue | Q1: Actual Variable Cost | R1: Actual Fixed Opex | S1: Actual Operating Profit | T1: Revenue Variance | U1: Profit Variance | V1: Budget Status | W1: Target Error Detection | X1: Target Audit Time Reduction
A2: 1 | B2: Q1 | C2: 0.5 | D2: 0.25 | E2: 0 | F2: 0.75 | G2: 104.16667 | H2: 156.25 | I2: 0 | J2: 260.41667 | K2: 52.083333 | L2: 4500 | M2: -4291.6667 | N2: -30791.667 | O2: 0.8 | W2: 0.9 | X2: 0.6
A3: 2 | B3: Q1 | C3: 1 | D3: 0.5 | E3: 0 | F3: 1.5 | G3: 208.33333 | H3: 312.5 | I3: 0 | J3: 520.83333 | K3: 104.16667 | L3: 4500 | M3: -4083.3333 | N3: -34875 | O3: 0.8 | W3: 0.9 | X3: 0.6
A4: 3 | B4: Q1 | C4: 1.5 | D4: 0.75 | E4: 0 | F4: 2.25 | G4: 312.5 | H4: 468.75 | I4: 0 | J4: 781.25 | K4: 156.25 | L4: 4500 | M4: -3875 | N4: -38750 | O4: 0.8 | W4: 0.9 | X4: 0.6
A5: 4 | B5: Q2 | C5: 2 | D5: 1 | E5: 0 | F5: 3 | G5: 416.66667 | H5: 625 | I5: 0 | J5: 1041.6667 | K5: 208.33333 | L5: 4500 | M5: -3666.6667 | N5: -42416.667 | O5: 0.8 | W5: 0.9 | X5: 0.6
A6: 5 | B6: Q2 | C6: 2.5 | D6: 1.25 | E6: 0 | F6: 3.75 | G6: 520.83333 | H6: 781.25 | I6: 0 | J6: 1302.0833 | K6: 260.41667 | L6: 4500 | M6: -3458.3333 | N6: -45875 | O6: 0.8 | W6: 0.9 | X6: 0.6
A7: 6 | B7: Q2 | C7: 3 | D7: 1.5 | E7: 0 | F7: 4.5 | G7: 625 | H7: 937.5 | I7: 0 | J7: 1562.5 | K7: 312.5 | L7: 4500 | M7: -3250 | N7: -49125 | O7: 0.8 | W7: 0.9 | X7: 0.6
A8: 7 | B8: Q3 | C8: 3.5 | D8: 1.75 | E8: 0 | F8: 5.25 | G8: 729.16667 | H8: 1093.75 | I8: 0 | J8: 1822.9167 | K8: 364.58333 | L8: 4500 | M8: -3041.6667 | N8: -52166.667 | O8: 0.8 | W8: 0.9 | X8: 0.6
A9: 8 | B9: Q3 | C9: 4 | D9: 2 | E9: 0 | F9: 6 | G9: 833.33333 | H9: 1250 | I9: 0 | J9: 2083.3333 | K9: 416.66667 | L9: 4500 | M9: -2833.3333 | N9: -55000 | O9: 0.8 | W9: 0.9 | X9: 0.6
A10: 9 | B10: Q3 | C10: 4.5 | D10: 2.25 | E10: 0 | F10: 6.75 | G10: 937.5 | H10: 1406.25 | I10: 0 | J10: 2343.75 | K10: 468.75 | L10: 4500 | M10: -2625 | N10: -57625 | O10: 0.8 | W10: 0.9 | X10: 0.6
A11: 10 | B11: Q4 | C11: 5 | D11: 2.5 | E11: 0 | F11: 7.5 | G11: 1041.6667 | H11: 1562.5 | I11: 0 | J11: 2604.1667 | K11: 520.83333 | L11: 4500 | M11: -2416.6667 | N11: -60041.667 | O11: 0.8 | W11: 0.9 | X11: 0.6
A12: 11 | B12: Q4 | C12: 5.5 | D12: 2.75 | E12: 0 | F12: 8.25 | G12: 1145.8333 | H12: 1718.75 | I12: 0 | J12: 2864.5833 | K12: 572.91667 | L12: 4500 | M12: -2208.3333 | N12: -62250 | O12: 0.8 | W12: 0.9 | X12: 0.6
A13: 12 | B13: Q4 | C13: 6 | D13: 3 | E13: 0 | F13: 9 | G13: 1250 | H13: 1875 | I13: 0 | J13: 3125 | K13: 625 | L13: 4500 | M13: -2000 | N13: -64250 | O13: 0.8 | W13: 0.9 | X13: 0.6
... A25: 24 | B25: Q8 | C25: 12 | D25: 6 | E25: 0 | F25: 18 | G25: 2500 | H25: 3750 | I25: 0 | J25: 6250 | K25: 1250 | L25: 4500 | M25: 500 | N25: -72000 | O25: 0.8 | W25: 0.9 | X25: 0.6

Sheet Sensitivity
A1: SAEIS | تحليل الحساسية
A2: اختبر تأثير أسعار الباقات والتكلفة المتغيرة وسرعة اكتساب العملاء على الربحية ونقطة التعادل.
A4: السيناريو | B4: سعر أساسي سنوي | C4: سعر احترافي سنوي | D4: عملاء أساسيون جدد/شهر | E4: عملاء احترافيون جدد/شهر | F4: تكلفة متغيرة % | G4: نقطة التعادل الشهرية | H4: فترة الاسترداد
A5: محافظ | B5: 2200 | C5: 6500 | D5: 0.25 | E5: 0.1 | F5: 0.3 | G5: =Inputs!$C$17/(1-F5) -> 6428.5714 | H5: يرتبط بالحالة التشغيلية في النموذج الأساسي
A6: أساسي | B6: 2500 | C6: 7500 | D6: 0.5 | E6: 0.25 | F6: 0.2 | G6: =Inputs!$C$17/(1-F6) -> 5625 | H6: يرتبط بالحالة التشغيلية في النموذج الأساسي
A7: متفائل | B7: 2800 | C7: 8500 | D7: 0.75 | E7: 0.4 | F7: 0.15 | G7: =Inputs!$C$17/(1-F7) -> 5294.1176 | H7: يرتبط بالحالة التشغيلية في النموذج الأساسي

Sheet Three_Year_Forecast
A1: SAEIS | توقع الإيرادات والأرباح لثلاث سنوات
A2: توقع تخطيطي مبني على الافتراضات القابلة للتعديل في ورقة Inputs، وليس نتيجة فعلية أو ضمانًا ماليًا.
A4: السيناريو | B4: الشهر | C4: السنة | D4: العملاء الأساسيون | E4: العملاء الاحترافيون | F4: إجمالي العملاء | G4: الإيراد | H4: التكلفة المتغيرة | I4: الربح التشغيلي | J4: التدفق النقدي التراكمي
A5: محافظ | B5: 1 | C5: 1 | D5: 0.25 | E5: 0.1 | F5: 0.35 | G5: 100.20833 | H5: 30.0625 | I5: -4429.8542 | J5: -30929.854
A6: محافظ | B6: 2 | C6: 1 | D6: 0.5 | E6: 0.2 | F6: 0.7 | G6: 200.41667 | H6: 60.125 | I6: -4359.7083 | J6: -35289.562
A7: محافظ | B7: 3 | C7: 1 | D7: 0.75 | E7: 0.3 | F7: 1.05 | G7: 300.625 | H7: 90.1875 | I7: -4289.5625 | J7: -39579.125
A8: محافظ | B8: 4 | C8: 1 | D8: 1 | E8: 0.4 | F8: 1.4 | G8: 400.83333 | H8: 120.25 | I8: -4219.4167 | J8: -43798.542
A9: محافظ | B9: 5 | C9: 1 | D9: 1.25 | E9: 0.5 | F9: 1.75 | G9: 501.04167 | H9: 150.3125 | I9: -4149.2708 | J9: -47947.812
A10: محافظ | B10: 6 | C10: 1 | D10: 1.5 | E10: 0.6 | F10: 2.1 | G10: 601.25 | H10: 180.375 | I10: -4079.125 | J10: -52026.938
A11: محافظ | B11: 7 | C11: 1 | D11: 1.75 | E11: 0.7 | F11: 2.45 | G11: 701.45833 | H11: 210.4375 | I11: -4008.9792 | J11: -56035.917
A12: محافظ | B12: 8 | C12: 1 | D12: 2 | E12: 0.8 | F12: 2.8 | G12: 801.66667 | H12: 240.5 | I12: -3938.8333 | J12: -59974.75
A13: محافظ | B13: 9 | C13: 1 | D13: 2.25 | E13: 0.9 | F13: 3.15 | G13: 901.875 | H13: 270.5625 | I13: -3868.6875 | J13: -63843.438
A14: محافظ | B14: 10 | C14: 1 | D14: 2.5 | E14: 1 | F14: 3.5 | G14: 1002.0833 | H14: 300.625 | I14: -3798.5417 | J14: -67641.979
A15: محافظ | B15: 11 | C15: 1 | D15: 2.75 | E15: 1.1 | F15: 3.85 | G15: 1102.2917 | H15: 330.6875 | I15: -3728.3958 | J15: -71370.375
A16: محافظ | B16: 12 | C16: 1 | D16: 3 | E16: 1.2 | F16: 4.2 | G16: 1202.5 | H16: 360.75 | I16: -3658.25 | J16: -75028.625
... A112: متفائل | B112: 36 | C112: 3 | D112: 27 | E112: 14.4 | F112: 41.4 | G112: 16470 | H112: 2470.5 | I112: 9499.5 | J112: 70490.75
A115: ملخص السنوات
A116: السيناريو | B116: السنة | C116: الإيراد | D116: الربح التشغيلي | E116: التدفق النقدي في نهاية السنة | F116: العملاء في نهاية السنة | G116: هامش المساهمة
A117: محافظ | B117: 1 | C117: 7816.25 | D117: -48528.625 | E117: -75028.625 | F117: 4.2 | G117: 0.7
A118: محافظ | B118: 2 | C118: 22246.25 | D118: -38427.625 | E118: -113456.25 | F118: 8.4 | G118: 0.7
A119: محافظ | B119: 3 | C119: 36676.25 | D119: -28326.625 | E119: -141782.88 | F119: 12.6 | G119: 0.7
A120: أساسي | B120: 1 | C120: 20312.5 | D120: -37750 | E120: -64250 | F120: 9 | G120: 0.8
A121: أساسي | B121: 2 | C121: 57812.5 | D121: -7750 | E121: -72000 | F121: 18 | G121: 0.8
A122: أساسي | B122: 3 | C122: 95312.5 | D122: 22250 | E122: -49750 | F122: 27 | G122: 0.8
A123: متفائل | B123: 1 | C123: 35685 | D123: -23667.75 | E123: -50167.75 | F123: 13.8 | G123: 0.85
A124: متفائل | B124: 2 | C124: 101565 | D124: 32330.25 | E124: -17837.5 | F124: 27.6 | G124: 0.85
A125: متفائل | B125: 3 | C125: 167445 | D125: 88328.25 | E125: 70490.75 | F125: 41.4 | G125: 0.85

Sheet Sensitivity_3Y
A1: SAEIS | تحليل حساسية إيرادات السنة الثالثة
A2: التأثير المشترك لتغير السعر وسرعة اكتساب العملاء، مع ثبات باقي الافتراضات.
A4: مضاعف نمو العملاء / مضاعف السعر | B4: 0.8x السعر | C4: 1.0x السعر | D4: 1.2x السعر
A5: 0.5x نمو العملاء | B5: 38125 | C5: 47656.25 | D5: 57187.5
A6: 1.0x نمو العملاء | B6: 76250 | C6: 95312.5 | D6: 114375
A7: 1.5x نمو العملاء | B7: 114375 | C7: 142968.75 | D7: 171562.5
A10: طريقة القراءة
A11: كل خلية تمثل إيراد السنة الثالثة عند تغيير سعر الباقات ومعدل اكتساب العملاء مقارنة بالافتراض الأساسي. استخدم القيم كأداة نقاش للمخاطر، لا كهدف مضمون.
